codesys/__init__.py
codesys/agent.py
codesys/async_enhanced_agent.py
codesys/enhanced_agent.py
codesys-0.1.6.dist-info/METADATA
codesys-0.1.6.dist-info/WHEEL
codesys-0.1.6.dist-info/top_level.txt
codesys-0.1.6.dist-info/RECORD
